[{"__symbolic":"module","version":4,"metadata":{"FieldWriteComponent":{"__symbolic":"class","extends":{"__symbolic":"reference","module":"./abstract-field-write.component","name":"AbstractFieldWriteComponent","line":22,"character":41},"decorators":[{"__symbolic":"call","expression":{"__symbolic":"reference","module":"@angular/core","name":"Component","line":11,"character":1},"arguments":[{"selector":"ccd-field-write","template":"\n    <div [hidden]=\"caseField.hidden\" [class.grey-bar]=\"canHaveGreyBar && !caseField.hiddenCannotChange\">\n      <ng-container #fieldContainer></ng-container>\n    </div>\n  ","styles":["\n    .form :host::ng-deep .grey-bar>*>.form-group,.form :host::ng-deep .grey-bar>*>dl.case-field{margin-left:15px;padding-left:15px}.form :host::ng-deep .grey-bar>*>.form-group:not(.form-group-error),.form :host::ng-deep .grey-bar>*>dl.case-field:not(.form-group-error){border-left:solid 5px #b1b4b6}.form :host::ng-deep .grey-bar>*>.form-group input:not(.inline-block),.form :host::ng-deep .grey-bar>*>.form-group select:not(.inline-block),.form :host::ng-deep .grey-bar>*>.form-group textarea:not(.inline-block),.form :host::ng-deep .grey-bar>*>dl.case-field input:not(.inline-block),.form :host::ng-deep .grey-bar>*>dl.case-field select:not(.inline-block),.form :host::ng-deep .grey-bar>*>dl.case-field textarea:not(.inline-block){display:block}\n  "]}]}],"members":{"caseFields":[{"__symbolic":"property","decorators":[{"__symbolic":"call","expression":{"__symbolic":"reference","module":"@angular/core","name":"Input","line":27,"character":3}}]}],"fieldContainer":[{"__symbolic":"property","decorators":[{"__symbolic":"call","expression":{"__symbolic":"reference","module":"@angular/core","name":"ViewChild","line":30,"character":3},"arguments":["fieldContainer",{"read":{"__symbolic":"reference","module":"@angular/core","name":"ViewContainerRef","line":30,"character":38}}]}]}],"__ctor__":[{"__symbolic":"constructor","parameters":[{"__symbolic":"reference","module":"@angular/core","name":"ComponentFactoryResolver","line":33,"character":32},{"__symbolic":"reference","module":"../palette.service","name":"PaletteService","line":34,"character":38}]}],"addValidators":[{"__symbolic":"method"}],"ngOnInit":[{"__symbolic":"method"}]}}}}]